geography_toolkit/__init__.py
geography_toolkit/core.py
geography_toolkit-0.1.0.dist-info/LICENCE
geography_toolkit-0.1.0.dist-info/METADATA
geography_toolkit-0.1.0.dist-info/WHEEL
geography_toolkit-0.1.0.dist-info/top_level.txt
geography_toolkit-0.1.0.dist-info/RECORD
