Metadata-Version: 2.1
Name: geography_toolkit
Version: 0.1.0
Summary: Un package Python pour la géographie
Home-page: https://github.com/Zakiyou/geography_toolkit.git
Author: BABABODI Zakiyou
Author-email: zakiyoubababodi@gmail.com
Classifier: Programming Language :: Python :: 3
Classifier: License :: OSI Approved :: MIT License
Classifier: Operating System :: OS Independent
Requires-Python: >=3.6
License-File: LICENCE
